README.md
setup.py
limsmock/__init__.py
limsmock/constants.py
limsmock/filter.py
limsmock/server.py
limsmock/store.py
limsmock.egg-info/PKG-INFO
limsmock.egg-info/SOURCES.txt
limsmock.egg-info/dependency_links.txt
limsmock.egg-info/entry_points.txt
limsmock.egg-info/top_level.txt
limsmock/demo/__init__.py
limsmock/demo/demo.py
limsmock/routers/__init__.py
limsmock/routers/artifactgroups.py
limsmock/routers/artifacts.py
limsmock/routers/automations.py
limsmock/routers/containers.py
limsmock/routers/containertypes.py
limsmock/routers/controltypes.py
limsmock/routers/files.py
limsmock/routers/instruments.py
limsmock/routers/labs.py
limsmock/routers/permissions.py
limsmock/routers/processes.py
limsmock/routers/processtemplates.py
limsmock/routers/processtypes.py
limsmock/routers/projects.py
limsmock/routers/protocols.py
limsmock/routers/reagentkits.py
limsmock/routers/reagentlots.py
limsmock/routers/reagenttypes.py
limsmock/routers/researchers.py
limsmock/routers/roles.py
limsmock/routers/samples.py
limsmock/routers/udfs.py
limsmock/routers/udts.py
limsmock/routers/workflows.py
tests/__init__.py
tests/conftest.py
tests/test_1.py