Metadata-Version: 2.1
Name: limsmock
Version: 1.0.0
Summary: Mock for the genologics package
Home-page: https://github.com/Clinical-Genomics/limsmock
Author: Maya Brandi
Author-email: maya.brandi@scilifelab.se
License: UNKNOWN
Platform: UNKNOWN
Classifier: Programming Language :: Python :: 3
Classifier: License :: OSI Approved :: MIT License
Classifier: Operating System :: OS Independent
Requires-Python: >=3.6
